sqlinjector/__init__.py
sqlinjector/cli.py
sqlinjector/exceptions.py
sqlinjector/injector.py
sqlinjector/models.py
sqlinjector/payloads.py
sqlinjector/scanner.py
sqlinjector/utils.py
sqlinjector-1.0.1.dist-info/METADATA
sqlinjector-1.0.1.dist-info/WHEEL
sqlinjector-1.0.1.dist-info/entry_points.txt
sqlinjector-1.0.1.dist-info/top_level.txt
sqlinjector-1.0.1.dist-info/RECORD
